<?xml version="1.0" encoding="UTF-8"?>
<!--Generated by Oracle BI Publisher 11.1.1.7.140715 -Dataengine, datamodel:/Rapoarte diverse/Rapoarte COFOG3-OPC-Superior/Rap-COFOG3-OPC-BD_dm.xdm -->
<DATA_DS><P_SECB>01</P_SECB><P_DENSEC>Bugetul de stat (administratie centrala)</P_DENSEC><P_CUI>33354101</P_CUI><P_DEN>ACADEMIA DE STIINTE ALE SECURITATII NATIONALE</P_DEN><P_ZI>31-JAN-17</P_ZI>
<G_1>
<TIP_CLASIF>Venit</TIP_CLASIF>
<COD_FUNCTIONAL>370100</COD_FUNCTIONAL>
<DENUMIRE_CF>Donatii si sponsorizari</DENUMIRE_CF>
<COD_ECONOMIC>000000</COD_ECONOMIC>
<COD_PROGRAM_BUGETAR>00</COD_PROGRAM_BUGETAR>
<SURSA_FINANTARE>F-Integral venituri proprii</SURSA_FINANTARE>
<RULAJ>3000</RULAJ>
<TOTALV>3000</TOTALV>
<TOTALC></TOTALC>
</G_1>
<G_1>
<TIP_CLASIF>Venit</TIP_CLASIF>
<COD_FUNCTIONAL>401503</COD_FUNCTIONAL>
<DENUMIRE_CF>Sume utilizate de alte institutii din excedentul anului precedent</DENUMIRE_CF>
<COD_ECONOMIC>000000</COD_ECONOMIC>
<COD_PROGRAM_BUGETAR>00</COD_PROGRAM_BUGETAR>
<SURSA_FINANTARE>F-Integral venituri proprii</SURSA_FINANTARE>
<RULAJ>23000</RULAJ>
<TOTALV>23000</TOTALV>
<TOTALC></TOTALC>
</G_1>
<G_1>
<TIP_CLASIF>Venit</TIP_CLASIF>
<COD_FUNCTIONAL>423800</COD_FUNCTIONAL>
<DENUMIRE_CF>Subventii de la bugetul de stat pentru  institutii si servicii publice sau activitati finantate integral din venituri proprii</DENUMIRE_CF>
<COD_ECONOMIC>000000</COD_ECONOMIC>
<COD_PROGRAM_BUGETAR>00</COD_PROGRAM_BUGETAR>
<SURSA_FINANTARE>F-Integral venituri proprii</SURSA_FINANTARE>
<RULAJ>117500</RULAJ>
<TOTALV>117500</TOTALV>
<TOTALC></TOTALC>
</G_1>
<G_1>
<TIP_CLASIF>Cheltuiala</TIP_CLASIF>
<COD_FUNCTIONAL>652500</COD_FUNCTIONAL>
<DENUMIRE_CF>Cercetare  si dezvoltare   pentru invatamant</DENUMIRE_CF>
<COD_ECONOMIC>100101</COD_ECONOMIC>
<DENUMIRE_CE>Salarii de baza</DENUMIRE_CE>
<COD_PROGRAM_BUGETAR>00</COD_PROGRAM_BUGETAR>
<SURSA_FINANTARE>F-Integral venituri proprii</SURSA_FINANTARE>
<RULAJ>1310</RULAJ>
<TOTALV></TOTALV>
<TOTALC>1310</TOTALC>
</G_1>
<G_1>
<TIP_CLASIF>Cheltuiala</TIP_CLASIF>
<COD_FUNCTIONAL>652500</COD_FUNCTIONAL>
<DENUMIRE_CF>Cercetare  si dezvoltare   pentru invatamant</DENUMIRE_CF>
<COD_ECONOMIC>100103</COD_ECONOMIC>
<DENUMIRE_CE>Indemnizatie de conducere</DENUMIRE_CE>
<COD_PROGRAM_BUGETAR>00</COD_PROGRAM_BUGETAR>
<SURSA_FINANTARE>F-Integral venituri proprii</SURSA_FINANTARE>
<RULAJ>174</RULAJ>
<TOTALV></TOTALV>
<TOTALC>174</TOTALC>
</G_1>
<G_1>
<TIP_CLASIF>Cheltuiala</TIP_CLASIF>
<COD_FUNCTIONAL>652500</COD_FUNCTIONAL>
<DENUMIRE_CF>Cercetare  si dezvoltare   pentru invatamant</DENUMIRE_CF>
<COD_ECONOMIC>100104</COD_ECONOMIC>
<DENUMIRE_CE>Spor de vechime</DENUMIRE_CE>
<COD_PROGRAM_BUGETAR>00</COD_PROGRAM_BUGETAR>
<SURSA_FINANTARE>F-Integral venituri proprii</SURSA_FINANTARE>
<RULAJ>148</RULAJ>
<TOTALV></TOTALV>
<TOTALC>148</TOTALC>
</G_1>
<G_1>
<TIP_CLASIF>Cheltuiala</TIP_CLASIF>
<COD_FUNCTIONAL>652500</COD_FUNCTIONAL>
<DENUMIRE_CF>Cercetare  si dezvoltare   pentru invatamant</DENUMIRE_CF>
<COD_ECONOMIC>100301</COD_ECONOMIC>
<DENUMIRE_CE>Contributii de asigurari sociale de stat</DENUMIRE_CE>
<COD_PROGRAM_BUGETAR>00</COD_PROGRAM_BUGETAR>
<SURSA_FINANTARE>F-Integral venituri proprii</SURSA_FINANTARE>
<RULAJ>261</RULAJ>
<TOTALV></TOTALV>
<TOTALC>261</TOTALC>
</G_1>
<G_1>
<TIP_CLASIF>Cheltuiala</TIP_CLASIF>
<COD_FUNCTIONAL>652500</COD_FUNCTIONAL>
<DENUMIRE_CF>Cercetare  si dezvoltare   pentru invatamant</DENUMIRE_CF>
<COD_ECONOMIC>100302</COD_ECONOMIC>
<DENUMIRE_CE>Contributii de asigurari de somaj </DENUMIRE_CE>
<COD_PROGRAM_BUGETAR>00</COD_PROGRAM_BUGETAR>
<SURSA_FINANTARE>F-Integral venituri proprii</SURSA_FINANTARE>
<RULAJ>8</RULAJ>
<TOTALV></TOTALV>
<TOTALC>8</TOTALC>
</G_1>
<G_1>
<TIP_CLASIF>Cheltuiala</TIP_CLASIF>
<COD_FUNCTIONAL>652500</COD_FUNCTIONAL>
<DENUMIRE_CF>Cercetare  si dezvoltare   pentru invatamant</DENUMIRE_CF>
<COD_ECONOMIC>100303</COD_ECONOMIC>
<DENUMIRE_CE>Contributii de asigurari sociale de sanatate </DENUMIRE_CE>
<COD_PROGRAM_BUGETAR>00</COD_PROGRAM_BUGETAR>
<SURSA_FINANTARE>F-Integral venituri proprii</SURSA_FINANTARE>
<RULAJ>85</RULAJ>
<TOTALV></TOTALV>
<TOTALC>85</TOTALC>
</G_1>
<G_1>
<TIP_CLASIF>Cheltuiala</TIP_CLASIF>
<COD_FUNCTIONAL>652500</COD_FUNCTIONAL>
<DENUMIRE_CF>Cercetare  si dezvoltare   pentru invatamant</DENUMIRE_CF>
<COD_ECONOMIC>100306</COD_ECONOMIC>
<DENUMIRE_CE>Contributii pentru concedii si indemnizatii</DENUMIRE_CE>
<COD_PROGRAM_BUGETAR>00</COD_PROGRAM_BUGETAR>
<SURSA_FINANTARE>F-Integral venituri proprii</SURSA_FINANTARE>
<RULAJ>14</RULAJ>
<TOTALV></TOTALV>
<TOTALC>14</TOTALC>
</G_1>
<G_1>
<TIP_CLASIF>Cheltuiala</TIP_CLASIF>
<COD_FUNCTIONAL>652500</COD_FUNCTIONAL>
<DENUMIRE_CF>Cercetare  si dezvoltare   pentru invatamant</DENUMIRE_CF>
<COD_ECONOMIC>592600</COD_ECONOMIC>
<DENUMIRE_CE>Sume acordate membrilor academiilor</DENUMIRE_CE>
<COD_PROGRAM_BUGETAR>00</COD_PROGRAM_BUGETAR>
<SURSA_FINANTARE>F-Integral venituri proprii</SURSA_FINANTARE>
<RULAJ>74108</RULAJ>
<TOTALV></TOTALV>
<TOTALC>74108</TOTALC>
</G_1>
<TOTVEN>143500</TOTVEN>
<TOTCHELT>76108</TOTCHELT>
</DATA_DS>